{
  "updated_at": "2026-07-10T11:29:43.846622Z",
  "frames": [
    {
      "timestamp": "20260708111500",
      "iso": "2026-07-08T11:15:00Z",
      "png": "radar_frames/radar_20260708111500.png",
      "bounds": [
        [
          45.6799459504888,
          1.4633015102566647
        ],
        [
          56.21935650980597,
          23.804402626309162
        ]
      ],
      "sources": {
        "main_ts": "20260708111500",
        "cz_ts": "20260708111500",
        "sk_ts": "20260708110500",
        "de_ts": "20260708111000",
        "hu_ts": "20260708110500",
        "hu_href": "radar_composite-refl2D-20260708_1105.nc.zip",
        "iso": "2026-07-08T11:15:00Z"
      }
    },
    {
      "timestamp": "20260708150000",
      "iso": "2026-07-08T15:00:00Z",
      "png": "radar_frames/radar_20260708150000.png",
      "bounds": [
        [
          45.6799459504888,
          1.4633015102566647
        ],
        [
          56.21935650980597,
          23.804402626309162
        ]
      ],
      "sources": {
        "main_ts": "20260708150000",
        "cz_ts": "20260708150000",
        "sk_ts": "20260708145500",
        "de_ts": "20260708145500",
        "hu_ts": "20260708145500",
        "hu_href": "radar_composite-refl2D-20260708_1455.nc.zip",
        "iso": "2026-07-08T15:00:00Z"
      }
    },
    {
      "timestamp": "20260708164000",
      "iso": "2026-07-08T16:40:00Z",
      "png": "radar_frames/radar_20260708164000.png",
      "bounds": [
        [
          45.6799459504888,
          1.4633015102566647
        ],
        [
          56.21935650980597,
          23.804402626309162
        ]
      ],
      "sources": {
        "main_ts": "20260708164000",
        "cz_ts": "20260708164000",
        "sk_ts": "20260708163500",
        "de_ts": "20260708163500",
        "hu_ts": "20260708163500",
        "hu_href": "radar_composite-refl2D-20260708_1635.nc.zip",
        "iso": "2026-07-08T16:40:00Z"
      }
    },
    {
      "timestamp": "20260708180500",
      "iso": "2026-07-08T18:05:00Z",
      "png": "radar_frames/radar_20260708180500.png",
      "bounds": [
        [
          45.6799459504888,
          1.4633015102566647
        ],
        [
          56.21935650980597,
          23.804402626309162
        ]
      ],
      "sources": {
        "main_ts": "20260708180500",
        "cz_ts": "20260708180500",
        "sk_ts": "20260708180000",
        "de_ts": "20260708180000",
        "hu_ts": "20260708180000",
        "hu_href": "radar_composite-refl2D-20260708_1800.nc.zip",
        "iso": "2026-07-08T18:05:00Z"
      }
    },
    {
      "timestamp": "20260708194500",
      "iso": "2026-07-08T19:45:00Z",
      "png": "radar_frames/radar_20260708194500.png",
      "bounds": [
        [
          45.6799459504888,
          1.4633015102566647
        ],
        [
          56.21935650980597,
          23.804402626309162
        ]
      ],
      "sources": {
        "main_ts": "20260708194500",
        "cz_ts": "20260708194500",
        "sk_ts": "20260708194000",
        "de_ts": "20260708194000",
        "hu_ts": "20260708194000",
        "hu_href": "radar_composite-refl2D-20260708_1940.nc.zip",
        "iso": "2026-07-08T19:45:00Z"
      }
    },
    {
      "timestamp": "20260708204500",
      "iso": "2026-07-08T20:45:00Z",
      "png": "radar_frames/radar_20260708204500.png",
      "bounds": [
        [
          45.6799459504888,
          1.4633015102566647
        ],
        [
          56.21935650980597,
          23.804402626309162
        ]
      ],
      "sources": {
        "main_ts": "20260708204500",
        "cz_ts": "20260708204500",
        "sk_ts": "20260708204000",
        "de_ts": "20260708204000",
        "hu_ts": "20260708204000",
        "hu_href": "radar_composite-refl2D-20260708_2040.nc.zip",
        "iso": "2026-07-08T20:45:00Z"
      }
    },
    {
      "timestamp": "20260708214500",
      "iso": "2026-07-08T21:45:00Z",
      "png": "radar_frames/radar_20260708214500.png",
      "bounds": [
        [
          45.6799459504888,
          1.4633015102566647
        ],
        [
          56.21935650980597,
          23.804402626309162
        ]
      ],
      "sources": {
        "main_ts": "20260708214500",
        "cz_ts": "20260708214500",
        "sk_ts": "20260708214000",
        "de_ts": "20260708214000",
        "hu_ts": "20260708214000",
        "hu_href": "radar_composite-refl2D-20260708_2140.nc.zip",
        "iso": "2026-07-08T21:45:00Z"
      }
    },
    {
      "timestamp": "20260708224500",
      "iso": "2026-07-08T22:45:00Z",
      "png": "radar_frames/radar_20260708224500.png",
      "bounds": [
        [
          45.6799459504888,
          1.4633015102566647
        ],
        [
          56.21935650980597,
          23.804402626309162
        ]
      ],
      "sources": {
        "main_ts": "20260708224500",
        "cz_ts": "20260708224500",
        "sk_ts": "20260708224000",
        "de_ts": "20260708224000",
        "hu_ts": "20260708224000",
        "hu_href": "radar_composite-refl2D-20260708_2240.nc.zip",
        "iso": "2026-07-08T22:45:00Z"
      }
    },
    {
      "timestamp": "20260708234500",
      "iso": "2026-07-08T23:45:00Z",
      "png": "radar_frames/radar_20260708234500.png",
      "bounds": [
        [
          45.6799459504888,
          1.4633015102566647
        ],
        [
          56.21935650980597,
          23.804402626309162
        ]
      ],
      "sources": {
        "main_ts": "20260708234500",
        "cz_ts": "20260708234500",
        "sk_ts": "20260708234000",
        "de_ts": "20260708234000",
        "hu_ts": "20260708234000",
        "hu_href": "radar_composite-refl2D-20260708_2340.nc.zip",
        "iso": "2026-07-08T23:45:00Z"
      }
    },
    {
      "timestamp": "20260709011500",
      "iso": "2026-07-09T01:15:00Z",
      "png": "radar_frames/radar_20260709011500.png",
      "bounds": [
        [
          45.6799459504888,
          1.4633015102566647
        ],
        [
          56.21935650980597,
          23.804402626309162
        ]
      ],
      "sources": {
        "main_ts": "20260709011500",
        "cz_ts": "20260709011500",
        "sk_ts": "20260709011000",
        "de_ts": "20260709011000",
        "hu_ts": "20260709011000",
        "hu_href": "radar_composite-refl2D-20260709_0110.nc.zip",
        "iso": "2026-07-09T01:15:00Z"
      }
    },
    {
      "timestamp": "20260709051000",
      "iso": "2026-07-09T05:10:00Z",
      "png": "radar_frames/radar_20260709051000.png",
      "bounds": [
        [
          45.6799459504888,
          1.4633015102566647
        ],
        [
          56.21935650980597,
          23.804402626309162
        ]
      ],
      "sources": {
        "main_ts": "20260709051000",
        "cz_ts": "20260709051000",
        "sk_ts": "20260709050500",
        "de_ts": "20260709050500",
        "hu_ts": "20260709050500",
        "hu_href": "radar_composite-refl2D-20260709_0505.nc.zip",
        "iso": "2026-07-09T05:10:00Z"
      }
    },
    {
      "timestamp": "20260709083500",
      "iso": "2026-07-09T08:35:00Z",
      "png": "radar_frames/radar_20260709083500.png",
      "bounds": [
        [
          45.6799459504888,
          1.4633015102566647
        ],
        [
          56.21935650980597,
          23.804402626309162
        ]
      ],
      "sources": {
        "main_ts": "20260709083500",
        "cz_ts": "20260709083500",
        "sk_ts": "20260709083000",
        "de_ts": "20260709083000",
        "hu_ts": "20260709083000",
        "hu_href": "radar_composite-refl2D-20260709_0830.nc.zip",
        "iso": "2026-07-09T08:35:00Z"
      }
    },
    {
      "timestamp": "20260709113000",
      "iso": "2026-07-09T11:30:00Z",
      "png": "radar_frames/radar_20260709113000.png",
      "bounds": [
        [
          45.6799459504888,
          1.4633015102566647
        ],
        [
          56.21935650980597,
          23.804402626309162
        ]
      ],
      "sources": {
        "main_ts": "20260709113000",
        "cz_ts": "20260709113000",
        "sk_ts": "20260709112000",
        "de_ts": "20260709112500",
        "hu_ts": "20260709112500",
        "hu_href": "radar_composite-refl2D-20260709_1125.nc.zip",
        "iso": "2026-07-09T11:30:00Z"
      }
    },
    {
      "timestamp": "20260709140500",
      "iso": "2026-07-09T14:05:00Z",
      "png": "radar_frames/radar_20260709140500.png",
      "bounds": [
        [
          45.6799459504888,
          1.4633015102566647
        ],
        [
          56.21935650980597,
          23.804402626309162
        ]
      ],
      "sources": {
        "main_ts": "20260709140500",
        "cz_ts": "20260709140500",
        "sk_ts": "20260709135500",
        "de_ts": "20260709140000",
        "hu_ts": "20260709135500",
        "hu_href": "radar_composite-refl2D-20260709_1355.nc.zip",
        "iso": "2026-07-09T14:05:00Z"
      }
    },
    {
      "timestamp": "20260709163500",
      "iso": "2026-07-09T16:35:00Z",
      "png": "radar_frames/radar_20260709163500.png",
      "bounds": [
        [
          45.6799459504888,
          1.4633015102566647
        ],
        [
          56.21935650980597,
          23.804402626309162
        ]
      ],
      "sources": {
        "main_ts": "20260709163500",
        "cz_ts": "20260709163500",
        "sk_ts": "20260709162500",
        "de_ts": "20260709163000",
        "hu_ts": "20260709162500",
        "hu_href": "radar_composite-refl2D-20260709_1625.nc.zip",
        "iso": "2026-07-09T16:35:00Z"
      }
    },
    {
      "timestamp": "20260709181500",
      "iso": "2026-07-09T18:15:00Z",
      "png": "radar_frames/radar_20260709181500.png",
      "bounds": [
        [
          45.6799459504888,
          1.4633015102566647
        ],
        [
          56.21935650980597,
          23.804402626309162
        ]
      ],
      "sources": {
        "main_ts": "20260709181500",
        "cz_ts": "20260709181500",
        "sk_ts": "20260709181000",
        "de_ts": "20260709181000",
        "hu_ts": "20260709181000",
        "hu_href": "radar_composite-refl2D-20260709_1810.nc.zip",
        "iso": "2026-07-09T18:15:00Z"
      }
    },
    {
      "timestamp": "20260709200500",
      "iso": "2026-07-09T20:05:00Z",
      "png": "radar_frames/radar_20260709200500.png",
      "bounds": [
        [
          45.6799459504888,
          1.4633015102566647
        ],
        [
          56.21935650980597,
          23.804402626309162
        ]
      ],
      "sources": {
        "main_ts": "20260709200500",
        "cz_ts": "20260709200500",
        "sk_ts": "20260709200000",
        "de_ts": "20260709200000",
        "hu_ts": "20260709200000",
        "hu_href": "radar_composite-refl2D-20260709_2000.nc.zip",
        "iso": "2026-07-09T20:05:00Z"
      }
    },
    {
      "timestamp": "20260709213500",
      "iso": "2026-07-09T21:35:00Z",
      "png": "radar_frames/radar_20260709213500.png",
      "bounds": [
        [
          45.6799459504888,
          1.4633015102566647
        ],
        [
          56.21935650980597,
          23.804402626309162
        ]
      ],
      "sources": {
        "main_ts": "20260709213500",
        "cz_ts": "20260709213500",
        "sk_ts": "20260709213000",
        "de_ts": "20260709213500",
        "hu_ts": "20260709213000",
        "hu_href": "radar_composite-refl2D-20260709_2130.nc.zip",
        "iso": "2026-07-09T21:35:00Z"
      }
    },
    {
      "timestamp": "20260709225000",
      "iso": "2026-07-09T22:50:00Z",
      "png": "radar_frames/radar_20260709225000.png",
      "bounds": [
        [
          45.6799459504888,
          1.4633015102566647
        ],
        [
          56.21935650980597,
          23.804402626309162
        ]
      ],
      "sources": {
        "main_ts": "20260709225000",
        "cz_ts": "20260709225000",
        "sk_ts": "20260709224500",
        "de_ts": "20260709224500",
        "hu_ts": "20260709224500",
        "hu_href": "radar_composite-refl2D-20260709_2245.nc.zip",
        "iso": "2026-07-09T22:50:00Z"
      }
    },
    {
      "timestamp": "20260709235000",
      "iso": "2026-07-09T23:50:00Z",
      "png": "radar_frames/radar_20260709235000.png",
      "bounds": [
        [
          45.6799459504888,
          1.4633015102566647
        ],
        [
          56.21935650980597,
          23.804402626309162
        ]
      ],
      "sources": {
        "main_ts": "20260709235000",
        "cz_ts": "20260709235000",
        "sk_ts": "20260709234500",
        "de_ts": "20260709235000",
        "hu_ts": "20260709234500",
        "hu_href": "radar_composite-refl2D-20260709_2345.nc.zip",
        "iso": "2026-07-09T23:50:00Z"
      }
    },
    {
      "timestamp": "20260710011500",
      "iso": "2026-07-10T01:15:00Z",
      "png": "radar_frames/radar_20260710011500.png",
      "bounds": [
        [
          45.6799459504888,
          1.4633015102566647
        ],
        [
          56.21935650980597,
          23.804402626309162
        ]
      ],
      "sources": {
        "main_ts": "20260710011500",
        "cz_ts": "20260710011500",
        "sk_ts": "20260710011000",
        "de_ts": "20260710011000",
        "hu_ts": "20260710011000",
        "hu_href": "radar_composite-refl2D-20260710_0110.nc.zip",
        "iso": "2026-07-10T01:15:00Z"
      }
    },
    {
      "timestamp": "20260710051000",
      "iso": "2026-07-10T05:10:00Z",
      "png": "radar_frames/radar_20260710051000.png",
      "bounds": [
        [
          45.6799459504888,
          1.4633015102566647
        ],
        [
          56.21935650980597,
          23.804402626309162
        ]
      ],
      "sources": {
        "main_ts": "20260710051000",
        "cz_ts": "20260710051000",
        "sk_ts": "20260710050500",
        "de_ts": "20260710050500",
        "hu_ts": "20260710050500",
        "hu_href": "radar_composite-refl2D-20260710_0505.nc.zip",
        "iso": "2026-07-10T05:10:00Z"
      }
    },
    {
      "timestamp": "20260710083500",
      "iso": "2026-07-10T08:35:00Z",
      "png": "radar_frames/radar_20260710083500.png",
      "bounds": [
        [
          45.6799459504888,
          1.4633015102566647
        ],
        [
          56.21935650980597,
          23.804402626309162
        ]
      ],
      "sources": {
        "main_ts": "20260710083500",
        "cz_ts": "20260710083500",
        "sk_ts": "20260710083000",
        "de_ts": "20260710083000",
        "hu_ts": "20260710083000",
        "hu_href": "radar_composite-refl2D-20260710_0830.nc.zip",
        "iso": "2026-07-10T08:35:00Z"
      }
    },
    {
      "timestamp": "20260710112500",
      "iso": "2026-07-10T11:25:00Z",
      "png": "radar_frames/radar_20260710112500.png",
      "bounds": [
        [
          45.6799459504888,
          1.4633015102566647
        ],
        [
          56.21935650980597,
          23.804402626309162
        ]
      ],
      "sources": {
        "main_ts": "20260710112500",
        "cz_ts": "20260710112500",
        "sk_ts": "20260710112000",
        "de_ts": "20260710112500",
        "hu_ts": "20260710112000",
        "hu_href": "radar_composite-refl2D-20260710_1120.nc.zip",
        "iso": "2026-07-10T11:25:00Z"
      }
    }
  ]
}